[
  {
    "company": "AgraTech",
    "hybrid": "1024VIP",
    "totalProduction": "17419",
    "estimatedSilage": "24.9",
    "milkPerTon": "3643",
    "milkPerAcre": "31785",
    "diseaseScore": "1.1",
    "dmAtHarvest": "31%",
    "nel": "0.74",
    "tdn": "77.4",
    "cp": "8.3",
    "ivtdmd30": "76.6",
    "starch": "28.2",
    "wsc": "6.3",
    "adf": "24.0",
    "aNdf": "43.6",
    "dNdf30": "23.6",
    "nDfd30Percentage": "54.2",
    "year": "2019",
    "season": "Spring",
    "type": "Corn"
  },
  {
    "company": "AgraTech",
    "hybrid": "1024VIP",
    "totalProduction": "17419",
    "estimatedSilage": "24.9",
    "milkPerTon": "3643",
    "milkPerAcre": "31785",
    "diseaseScore": "1.1",
    "dmAtHarvest": "31%",
    "nel": "0.74",
    "tdn": "77.4",
    "cp": "8.3",
    "ivtdmd30": "76.6",
    "starch": "28.2",
    "wsc": "6.3",
    "adf": "24.0",
    "aNdf": "43.6",
    "dNdf30": "23.6",
    "nDfd30Percentage": "54.2",
    "year": "2020",
    "season": "Spring",
    "type": "Corn Silage"
  },
  {
    "company": "AgraTech",
    "hybrid": "85VT2P",
    "totalProduction": "18989",
    "estimatedSilage": "27.1",
    "milkPerTon": "3194",
    "milkPerAcre": "30369",
    "diseaseScore": "1.0",
    "dmAtHarvest": "47%",
    "nel": "0.68",
    "tdn": "71.5",
    "cp": "7.6",
    "ivtdmd30": "73.8",
    "starch": "25.3",
    "wsc": "6.0",
    "adf": "26.9",
    "aNdf": "48.3",
    "dNdf30": "24.2",
    "nDfd30Percentage": "50.2",
    "year": "2020",
    "season": "Spring",
    "type": "Corn Silage"
  },
  {
    "company": "AgraTech",
    "hybrid": "88VT2P",
    "totalProduction": "16198",
    "estimatedSilage": "23.1",
    "milkPerTon": "3234",
    "milkPerAcre": "26192",
    "diseaseScore": "2.1",
    "dmAtHarvest": "44%",
    "nel": "0.68",
    "tdn": "72.4",
    "cp": "7.4",
    "ivtdmd30": "72.2",
    "starch": "24.6",
    "wsc": "5.4",
    "adf": "28.4",
    "aNdf": "50.4",
    "dNdf30": "25.3",
    "nDfd30Percentage": "50.1",
    "year": "2020",
    "season": "Spring",
    "type": "Corn Silage"
  },
  {
    "company": "AgraTech",
    "hybrid": "908VIP",
    "totalProduction": "17239",
    "estimatedSilage": "24.6",
    "milkPerTon": "3548",
    "milkPerAcre": "30532",
    "diseaseScore": "0.9",
    "dmAtHarvest": "30%",
    "nel": "0.73",
    "tdn": "76.2",
    "cp": "8.3",
    "ivtdmd30": "74.5",
    "starch": "24.3",
    "wsc": "6.9",
    "adf": "26.0",
    "aNdf": "46.7",
    "dNdf30": "24.0",
    "nDfd30Percentage": "51.5",
    "year": "2020",
    "season": "Spring",
    "type": "Corn Silage"
  },
  {
    "company": "Augusta seed",
    "hybrid": "A1367-3220GT",
    "relativeMaturity": "117",
    "totalProduction": "17264",
    "estimatedSilage": "24.6",
    "milkPerTon": "3269",
    "milkPerAcre": "21557",
    "diseaseScore": "1.5",
    "dmAtHarvest": "48%",
    "nel": "0.68",
    "tdn": "72.9",
    "cp": "7.7",
    "ivtdmd30": "75.9",
    "starch": "27.6",
    "wsc": "5.4",
    "adf": "25.2",
    "aNdf": "45.9",
    "dNdf30": "24.1",
    "nDfd30Percentage": "52.6",
    "year": "2020",
    "season": "Spring",
    "type": "Corn Silage"
  },
  {
    "company": "Augusta seed",
    "hybrid": "A4465-3110GT",
    "relativeMaturity": "115",
    "totalProduction": "16574",
    "estimatedSilage": "23.7",
    "milkPerTon": "3546",
    "milkPerAcre": "29399",
    "diseaseScore": "1.2",
    "dmAtHarvest": "31%",
    "nel": "0.73",
    "tdn": "76.0",
    "cp": "9.1",
    "ivtdmd30": "76.2",
    "starch": "25.9",
    "wsc": "7.3",
    "adf": "23.5",
    "aNdf": "44.5",
    "dNdf30": "23.0",
    "nDfd30Percentage": "51.7",
    "year": "2020",
    "season": "Spring",
    "type": "Corn Silage"
  },
  {
    "company": "Augusta seed",
    "hybrid": "A4467-3220GT",
    "relativeMaturity": "115",
    "totalProduction": "16930",
    "estimatedSilage": "24.2",
    "milkPerTon": "3332",
    "milkPerAcre": "28294",
    "diseaseScore": "1.4",
    "dmAtHarvest": "41%",
    "nel": "0.69",
    "tdn": "73.5",
    "cp": "8.4",
    "ivtdmd30": "76.9",
    "starch": "26.2",
    "wsc": "6.8",
    "adf": "24.2",
    "aNdf": "45.6",
    "dNdf30": "24.3",
    "nDfd30Percentage": "53.8",
    "year": "2020",
    "season": "Spring",
    "type": "Corn Silage"
  },
  {
    "company": "Augusta seed",
    "hybrid": "A7768-3110GT",
    "relativeMaturity": "117",
    "totalProduction": "15459",
    "estimatedSilage": "16.9",
    "milkPerTon": "3247",
    "milkPerAcre": "18606",
    "diseaseScore": "1.0",
    "dmAtHarvest": "41%",
    "nel": "0.68",
    "tdn": "72.5",
    "cp": "8.3",
    "ivtdmd30": "74.4",
    "starch": "22.3",
    "wsc": "6.3",
    "adf": "27.6",
    "aNdf": "48.6",
    "dNdf30": "24.7",
    "nDfd30Percentage": "51.0",
    "year": "2020",
    "season": "Spring",
    "type": "Corn Silage"
  },
  {
    "company": "Augusta seed",
    "hybrid": "A8868 VT2Pro",
    "relativeMaturity": "118",
    "totalProduction": "18165",
    "estimatedSilage": "25.9",
    "milkPerTon": "3263",
    "milkPerAcre": "29428",
    "diseaseScore": "1.3",
    "dmAtHarvest": "47%",
    "nel": "0.69",
    "tdn": "72.0",
    "cp": "7.7",
    "ivtdmd30": "75.9",
    "starch": "27.5",
    "wsc": "5.7",
    "adf": "24.7",
    "aNdf": "45.4",
    "dNdf30": "23.2",
    "nDfd30Percentage": "51.4",
    "year": "2020",
    "season": "Spring",
    "type": "Corn Silage"
  },
  {
    "company": "Croplan Genetics",
    "hybrid": "S5700",
    "relativeMaturity": "118",
    "totalProduction": "18793",
    "estimatedSilage": "26.8",
    "milkPerTon": "3356",
    "milkPerAcre": "31541",
    "diseaseScore": "1.3",
    "dmAtHarvest": "47%",
    "nel": "0.70",
    "tdn": "73.7",
    "cp": "8.0",
    "ivtdmd30": "76.2",
    "starch": "31.0",
    "wsc": "5.1",
    "adf": "23.1",
    "aNdf": "42.4",
    "dNdf30": "20.7",
    "nDfd30Percentage": "48.9",
    "year": "2020",
    "season": "Spring",
    "type": "Corn Silage"
  },
  {
    "company": "Croplan Genetics",
    "hybrid": "S5900 vt2p",
    "relativeMaturity": "117",
    "totalProduction": "16626",
    "estimatedSilage": "23.8",
    "milkPerTon": "3492",
    "milkPerAcre": "21796",
    "diseaseScore": "0.6",
    "dmAtHarvest": "30%",
    "nel": "0.72",
    "tdn": "75.2",
    "cp": "10.2",
    "ivtdmd30": "74.0",
    "starch": "21.2",
    "wsc": "7.9",
    "adf": "24.9",
    "aNdf": "45.7",
    "dNdf30": "22.0",
    "nDfd30Percentage": "48.3",
    "year": "2020",
    "season": "Spring",
    "type": "Corn Silage"
  },
  {
    "company": "Dekalb",
    "hybrid": "DKC64-44RIB SS",
    "relativeMaturity": "119",
    "totalProduction": "14612",
    "estimatedSilage": "20.9",
    "milkPerTon": "3644",
    "milkPerAcre": "26670",
    "diseaseScore": "1.1",
    "dmAtHarvest": "32%",
    "nel": "0.74",
    "tdn": "77.4",
    "cp": "10.5",
    "ivtdmd30": "76.3",
    "starch": "25.4",
    "wsc": "6.1",
    "adf": "23.0",
    "aNdf": "43.0",
    "dNdf30": "21.5",
    "nDfd30Percentage": "50.1",
    "year": "2020",
    "season": "Spring",
    "type": "Corn Silage"
  },
  {
    "company": "Dekalb",
    "hybrid": "DKC68-69 VT2P",
    "relativeMaturity": "114",
    "totalProduction": "17014",
    "estimatedSilage": "24.3",
    "milkPerTon": "3289",
    "milkPerAcre": "28016",
    "diseaseScore": "1.3",
    "dmAtHarvest": "47%",
    "nel": "0.69",
    "tdn": "72.8",
    "cp": "7.4",
    "ivtdmd30": "74.6",
    "starch": "28.6",
    "wsc": "4.2",
    "adf": "25.1",
    "aNdf": "45.7",
    "dNdf30": "22.5",
    "nDfd30Percentage": "49.4",
    "year": "2020",
    "season": "Spring",
    "type": "Corn Silage"
  },
  {
    "company": "Dekalb",
    "hybrid": "DKC69-16 SS",
    "relativeMaturity": "118",
    "totalProduction": "16058",
    "estimatedSilage": "22.9",
    "milkPerTon": "3381",
    "milkPerAcre": "27122",
    "diseaseScore": "0.5",
    "dmAtHarvest": "43%",
    "nel": "0.70",
    "tdn": "74.2",
    "cp": "8.6",
    "ivtdmd30": "74.9",
    "starch": "26.7",
    "wsc": "5.4",
    "adf": "24.5",
    "aNdf": "45.2",
    "dNdf30": "22.1",
    "nDfd30Percentage": "48.9",
    "year": "2020",
    "season": "Spring",
    "type": "Corn Silage"
  },
  {
    "company": "Dekalb",
    "hybrid": "DKC69-99 TRECEPTA",
    "relativeMaturity": "119",
    "totalProduction": "18797",
    "estimatedSilage": "26.8",
    "milkPerTon": "3263",
    "milkPerAcre": "30676",
    "diseaseScore": "0.9",
    "dmAtHarvest": "49%",
    "nel": "0.69",
    "tdn": "72.2",
    "cp": "6.8",
    "ivtdmd30": "73.8",
    "starch": "28.7",
    "wsc": "4.5",
    "adf": "25.3",
    "aNdf": "46.2",
    "dNdf30": "22.2",
    "nDfd30Percentage": "48.0",
    "year": "2020",
    "season": "Spring",
    "type": "Corn Silage"
  },
  {
    "company": "Dekalb",
    "hybrid": "DKC70-64 SS",
    "relativeMaturity": "119",
    "totalProduction": "18319",
    "estimatedSilage": "26.2",
    "milkPerTon": "3076",
    "milkPerAcre": "28198",
    "diseaseScore": "0.8",
    "dmAtHarvest": "44%",
    "nel": "0.66",
    "tdn": "70.0",
    "cp": "8.7",
    "ivtdmd30": "71.1",
    "starch": "21.4",
    "wsc": "7.4",
    "adf": "26.9",
    "aNdf": "48.7",
    "dNdf30": "22.4",
    "nDfd30Percentage": "46.1",
    "year": "2020",
    "season": "Spring",
    "type": "Corn Silage"
  },
  {
    "company": "Dyna-Gro",
    "hybrid": "D55QC73",
    "relativeMaturity": "120",
    "totalProduction": "16086",
    "estimatedSilage": "23.0",
    "milkPerTon": "3656",
    "milkPerAcre": "29423",
    "diseaseScore": "1.6",
    "dmAtHarvest": "30%",
    "nel": "0.74",
    "tdn": "77.8",
    "cp": "10.3",
    "ivtdmd30": "77.3",
    "starch": "25.5",
    "wsc": "6.8",
    "adf": "22.9",
    "aNdf": "42.3",
    "dNdf30": "21.6",
    "nDfd30Percentage": "51.2",
    "year": "2020",
    "season": "Spring",
    "type": "Corn Silage"
  },
  {
    "company": "Dyna-Gro",
    "hybrid": "D55VC80",
    "relativeMaturity": "115",
    "totalProduction": "17639",
    "estimatedSilage": "25.2",
    "milkPerTon": "3675",
    "milkPerAcre": "32427",
    "diseaseScore": "1.5",
    "dmAtHarvest": "35%",
    "nel": "0.74",
    "tdn": "78.0",
    "cp": "9.8",
    "ivtdmd30": "77.7",
    "starch": "28.3",
    "wsc": "6.2",
    "adf": "21.4",
    "aNdf": "41.3",
    "dNdf30": "20.2",
    "nDfd30Percentage": "48.9",
    "year": "2020",
    "season": "Spring",
    "type": "Corn Silage"
  },
  {
    "company": "Dyna-Gro",
    "hybrid": "D57VC17",
    "relativeMaturity": "115",
    "totalProduction": "17840",
    "estimatedSilage": "25.5",
    "milkPerTon": "3279",
    "milkPerAcre": "29206",
    "diseaseScore": "2.1",
    "dmAtHarvest": "51%",
    "nel": "0.69",
    "tdn": "72.5",
    "cp": "7.8",
    "ivtdmd30": "75.5",
    "starch": "29.4",
    "wsc": "5.0",
    "adf": "23.7",
    "aNdf": "44.2",
    "dNdf30": "21.3",
    "nDfd30Percentage": "48.3",
    "year": "2020",
    "season": "Spring",
    "type": "Corn Silage"
  },
  {
    "company": "Dyna-Gro",
    "hybrid": "D58QC72",
    "relativeMaturity": "117",
    "totalProduction": "19271",
    "estimatedSilage": "27.6",
    "milkPerTon": "3148",
    "milkPerAcre": "22810",
    "diseaseScore": "0.9",
    "dmAtHarvest": "45%",
    "nel": "0.67",
    "tdn": "71.4",
    "cp": "8.4",
    "ivtdmd30": "74.2",
    "starch": "22.5",
    "wsc": "6.8",
    "adf": "26.9",
    "aNdf": "47.7",
    "dNdf30": "23.6",
    "nDfd30Percentage": "49.5",
    "year": "2020",
    "season": "Spring",
    "type": "Corn Silage"
  },
  {
    "company": "Dyna-Gro",
    "hybrid": "D58SS65",
    "relativeMaturity": "118",
    "totalProduction": "18962",
    "estimatedSilage": "27.1",
    "milkPerTon": "3328",
    "milkPerAcre": "31557",
    "diseaseScore": "1.0",
    "dmAtHarvest": "48%",
    "nel": "0.70",
    "tdn": "72.8",
    "cp": "8.0",
    "ivtdmd30": "76.4",
    "starch": "30.6",
    "wsc": "5.3",
    "adf": "22.5",
    "aNdf": "42.2",
    "dNdf30": "20.4",
    "nDfd30Percentage": "48.4",
    "year": "2020",
    "season": "Spring",
    "type": "Corn Silage"
  },
  {
    "company": "Local Seed",
    "hybrid": "LC1688 SSX",
    "relativeMaturity": "118",
    "totalProduction": "17738",
    "estimatedSilage": "25.3",
    "milkPerTon": "3405",
    "milkPerAcre": "30169",
    "diseaseScore": "1.1",
    "dmAtHarvest": "48%",
    "nel": "0.71",
    "tdn": "74.3",
    "cp": "8.0",
    "ivtdmd30": "77.6",
    "starch": "32.3",
    "wsc": "4.6",
    "adf": "22.0",
    "aNdf": "41.5",
    "dNdf30": "20.9",
    "nDfd30Percentage": "50.3",
    "year": "2020",
    "season": "Spring",
    "type": "Corn Silage"
  },
  {
    "company": "Local Seed",
    "hybrid": "LC1898 TC",
    "relativeMaturity": "116",
    "totalProduction": "18076",
    "estimatedSilage": "25.8",
    "milkPerTon": "3263",
    "milkPerAcre": "29470",
    "diseaseScore": "1.3",
    "dmAtHarvest": "48%",
    "nel": "0.69",
    "tdn": "72.3",
    "cp": "7.7",
    "ivtdmd30": "75.2",
    "starch": "27.4",
    "wsc": "5.6",
    "adf": "24.4",
    "aNdf": "45.4",
    "dNdf30": "22.3",
    "nDfd30Percentage": "49.3",
    "year": "2020",
    "season": "Spring",
    "type": "Corn Silage"
  },
  {
    "company": "Local Seed",
    "hybrid": "LC1506 VT2P ",
    "relativeMaturity": "118",
    "totalProduction": "17583",
    "estimatedSilage": "25.1",
    "milkPerTon": "3723",
    "milkPerAcre": "32766",
    "diseaseScore": "1.4",
    "dmAtHarvest": "34%",
    "nel": "0.76",
    "tdn": "77.7",
    "cp": "9.6",
    "ivtdmd30": "79.3",
    "starch": "31.2",
    "wsc": "5.5",
    "adf": "20.2",
    "aNdf": "38.8",
    "dNdf30": "20.7",
    "nDfd30Percentage": "53.3",
    "year": "2020",
    "season": "Spring",
    "type": "Corn Silage"
  },
  {
    "company": "Local Seed",
    "hybrid": "LC1707 VT2P",
    "relativeMaturity": "115",
    "totalProduction": "16980",
    "estimatedSilage": "24.3",
    "milkPerTon": "3347",
    "milkPerAcre": "28284",
    "diseaseScore": "1.3",
    "dmAtHarvest": "50%",
    "nel": "0.70",
    "tdn": "73.8",
    "cp": "7.8",
    "ivtdmd30": "75.5",
    "starch": "28.2",
    "wsc": "5.0",
    "adf": "24.2",
    "aNdf": "45.3",
    "dNdf30": "22.6",
    "nDfd30Percentage": "50.1",
    "year": "2020",
    "season": "Spring",
    "type": "Corn Silage"
  },
  {
    "company": "Local Seed",
    "hybrid": "LC1806 VT2P",
    "relativeMaturity": "117",
    "totalProduction": "17700",
    "estimatedSilage": "25.3",
    "milkPerTon": "3415",
    "milkPerAcre": "30295",
    "diseaseScore": "1.3",
    "dmAtHarvest": "46%",
    "nel": "0.71",
    "tdn": "74.3",
    "cp": "7.9",
    "ivtdmd30": "77.0",
    "starch": "31.6",
    "wsc": "5.7",
    "adf": "21.7",
    "aNdf": "42.7",
    "dNdf30": "21.9",
    "nDfd30Percentage": "51.3",
    "year": "2020",
    "season": "Spring",
    "type": "Corn Silage"
  },
  {
    "company": "MorCorn",
    "hybrid": "MC 4255",
    "relativeMaturity": "117",
    "totalProduction": "16638",
    "estimatedSilage": "23.8",
    "milkPerTon": "3648",
    "milkPerAcre": "30401",
    "diseaseScore": "1.2",
    "dmAtHarvest": "37%",
    "nel": "0.74",
    "tdn": "77.2",
    "cp": "8.2",
    "ivtdmd30": "78.8",
    "starch": "31.7",
    "wsc": "5.8",
    "adf": "20.4",
    "aNdf": "40.4",
    "dNdf30": "21.0",
    "nDfd30Percentage": "52.1",
    "year": "2020",
    "season": "Spring",
    "type": "Corn Silage"
  },
  {
    "company": "MorCorn",
    "hybrid": "MC 4319",
    "relativeMaturity": "112",
    "totalProduction": "16574",
    "estimatedSilage": "23.7",
    "milkPerTon": "3545",
    "milkPerAcre": "29390",
    "diseaseScore": "1.4",
    "dmAtHarvest": "34%",
    "nel": "0.73",
    "tdn": "75.6",
    "cp": "8.2",
    "ivtdmd30": "74.3",
    "starch": "26.0",
    "wsc": "6.7",
    "adf": "24.7",
    "aNdf": "45.0",
    "dNdf30": "21.8",
    "nDfd30Percentage": "48.4",
    "year": "2020",
    "season": "Spring",
    "type": "Corn Silage"
  },
  {
    "company": "MorCorn",
    "hybrid": "MC 4670",
    "relativeMaturity": "113",
    "totalProduction": "17578",
    "estimatedSilage": "25.1",
    "milkPerTon": "3259",
    "milkPerAcre": "28629",
    "diseaseScore": "0.8",
    "dmAtHarvest": "48%",
    "nel": "0.68",
    "tdn": "72.5",
    "cp": "8.0",
    "ivtdmd30": "75.2",
    "starch": "27.0",
    "wsc": "5.5",
    "adf": "25.0",
    "aNdf": "46.1",
    "dNdf30": "23.3",
    "nDfd30Percentage": "50.5",
    "year": "2020",
    "season": "Spring",
    "type": "Corn Silage"
  },
  {
    "company": "MorCorn",
    "hybrid": "MC 4725",
    "relativeMaturity": "116",
    "totalProduction": "19108",
    "estimatedSilage": "27.3",
    "milkPerTon": "3243",
    "milkPerAcre": "30994",
    "diseaseScore": "1.6",
    "dmAtHarvest": "49%",
    "nel": "0.68",
    "tdn": "72.0",
    "cp": "7.7",
    "ivtdmd30": "75.2",
    "starch": "26.8",
    "wsc": "5.3",
    "adf": "24.9",
    "aNdf": "45.9",
    "dNdf30": "22.4",
    "nDfd30Percentage": "48.7",
    "year": "2020",
    "season": "Spring",
    "type": "Corn Silage"
  },
  {
    "company": "Phoenix",
    "hybrid": "6507A3",
    "relativeMaturity": "117",
    "totalProduction": "17491",
    "estimatedSilage": "25.0",
    "milkPerTon": "3711",
    "milkPerAcre": "32472",
    "diseaseScore": "2.1",
    "dmAtHarvest": "35%",
    "nel": "0.75",
    "tdn": "77.9",
    "cp": "7.8",
    "ivtdmd30": "78.0",
    "starch": "33.6",
    "wsc": "5.1",
    "adf": "21.2",
    "aNdf": "40.8",
    "dNdf30": "21.4",
    "nDfd30Percentage": "52.6",
    "year": "2020",
    "season": "Spring",
    "type": "Corn Silage"
  },
  {
    "company": "Phoenix",
    "hybrid": "6542A4",
    "relativeMaturity": "115",
    "totalProduction": "20107",
    "estimatedSilage": "28.7",
    "milkPerTon": "3169",
    "milkPerAcre": "31906",
    "diseaseScore": "1.3",
    "dmAtHarvest": "44%",
    "nel": "0.67",
    "tdn": "70.8",
    "cp": "6.5",
    "ivtdmd30": "75.3",
    "starch": "30.3",
    "wsc": "4.4",
    "adf": "26.2",
    "aNdf": "45.9",
    "dNdf30": "23.8",
    "nDfd30Percentage": "52.1",
    "year": "2020",
    "season": "Spring",
    "type": "Corn Silage"
  },
  {
    "company": "Phoenix",
    "hybrid": "7402A4",
    "relativeMaturity": "116",
    "totalProduction": "20368",
    "estimatedSilage": "29.1",
    "milkPerTon": "3207",
    "milkPerAcre": "32679",
    "diseaseScore": "1.1",
    "dmAtHarvest": "50%",
    "nel": "0.68",
    "tdn": "71.8",
    "cp": "7.5",
    "ivtdmd30": "74.6",
    "starch": "27.4",
    "wsc": "5.2",
    "adf": "26.1",
    "aNdf": "47.4",
    "dNdf30": "25.0",
    "nDfd30Percentage": "53.0",
    "year": "2020",
    "season": "Spring",
    "type": "Corn Silage"
  },
  {
    "company": "Pioneer",
    "hybrid": "P1847 VYHR",
    "relativeMaturity": "118",
    "totalProduction": "18520",
    "estimatedSilage": "26.5",
    "milkPerTon": "3317",
    "milkPerAcre": "22983",
    "diseaseScore": "1.1",
    "dmAtHarvest": "46%",
    "nel": "0.69",
    "tdn": "73.2",
    "cp": "7.6",
    "ivtdmd30": "77.0",
    "starch": "28.9",
    "wsc": "5.4",
    "adf": "23.8",
    "aNdf": "44.3",
    "dNdf30": "22.9",
    "nDfd30Percentage": "51.7",
    "year": "2020",
    "season": "Spring",
    "type": "Corn Silage"
  },
  {
    "company": "Pioneer",
    "hybrid": "P1903 YHR",
    "relativeMaturity": "118",
    "totalProduction": "17326",
    "estimatedSilage": "24.7",
    "milkPerTon": "3441",
    "milkPerAcre": "29777",
    "diseaseScore": "1.4",
    "dmAtHarvest": "47%",
    "nel": "0.71",
    "tdn": "74.7",
    "cp": "7.6",
    "ivtdmd30": "78.2",
    "starch": "32.7",
    "wsc": "4.5",
    "adf": "22.4",
    "aNdf": "42.4",
    "dNdf30": "22.2",
    "nDfd30Percentage": "52.4",
    "year": "2020",
    "season": "Spring",
    "type": "Corn Silage"
  },
  {
    "company": "Seedway",
    "hybrid": "SW 8100GENSS (RIB) - Smartstack",
    "relativeMaturity": "118",
    "totalProduction": "16474",
    "estimatedSilage": "23.5",
    "milkPerTon": "3292",
    "milkPerAcre": "27023",
    "diseaseScore": "1.9",
    "dmAtHarvest": "48%",
    "nel": "0.69",
    "tdn": "72.9",
    "cp": "8.1",
    "ivtdmd30": "75.8",
    "starch": "27.8",
    "wsc": "4.8",
    "adf": "24.9",
    "aNdf": "45.4",
    "dNdf30": "23.1",
    "nDfd30Percentage": "51.1",
    "year": "2020",
    "season": "Spring",
    "type": "Corn Silage"
  },
  {
    "company": "Seedway",
    "hybrid": "SW7560GENVT2P",
    "relativeMaturity": "115",
    "totalProduction": "15826",
    "estimatedSilage": "22.6",
    "milkPerTon": "3485",
    "milkPerAcre": "27589",
    "diseaseScore": "1.6",
    "dmAtHarvest": "42%",
    "nel": "0.72",
    "tdn": "75.2",
    "cp": "8.5",
    "ivtdmd30": "77.4",
    "starch": "29.0",
    "wsc": "5.3",
    "adf": "22.8",
    "aNdf": "43.2",
    "dNdf30": "22.1",
    "nDfd30Percentage": "51.4",
    "year": "2020",
    "season": "Spring",
    "type": "Corn Silage"
  },
  {
    "company": "Seedway",
    "hybrid": "SW8109VIP3111",
    "relativeMaturity": "117",
    "totalProduction": "18498",
    "estimatedSilage": "26.4",
    "milkPerTon": "3194",
    "milkPerAcre": "29523",
    "diseaseScore": "1.3",
    "dmAtHarvest": "48%",
    "nel": "0.68",
    "tdn": "71.7",
    "cp": "7.7",
    "ivtdmd30": "74.0",
    "starch": "26.3",
    "wsc": "5.5",
    "adf": "26.4",
    "aNdf": "47.8",
    "dNdf30": "24.7",
    "nDfd30Percentage": "51.8",
    "year": "2020",
    "season": "Spring",
    "type": "Corn Silage"
  },
  {
    "company": "Sun Prairie Seeds",
    "hybrid": "SP2928 3000GT",
    "relativeMaturity": "117",
    "totalProduction": "15891",
    "estimatedSilage": "22.7",
    "milkPerTon": "3340",
    "milkPerAcre": "19657",
    "diseaseScore": "0.8",
    "dmAtHarvest": "47%",
    "nel": "0.69",
    "tdn": "73.9",
    "cp": "9.0",
    "ivtdmd30": "75.2",
    "starch": "27.2",
    "wsc": "5.4",
    "adf": "24.5",
    "aNdf": "44.3",
    "dNdf30": "21.4",
    "nDfd30Percentage": "48.7",
    "year": "2020",
    "season": "Spring",
    "type": "Corn Silage"
  },
  {
    "company": "Syngenta",
    "hybrid": "NK1573-5222",
    "relativeMaturity": "116",
    "totalProduction": "16659",
    "estimatedSilage": "23.8",
    "milkPerTon": "3678",
    "milkPerAcre": "30674",
    "diseaseScore": "1.3",
    "dmAtHarvest": "30%",
    "nel": "0.75",
    "tdn": "77.8",
    "cp": "9.9",
    "ivtdmd30": "75.8",
    "starch": "27.4",
    "wsc": "6.3",
    "adf": "22.7",
    "aNdf": "42.6",
    "dNdf30": "21.4",
    "nDfd30Percentage": "50.3",
    "year": "2020",
    "season": "Spring",
    "type": "Corn Silage"
  },
  {
    "company": "Syngenta",
    "hybrid": "NK1677-3110",
    "relativeMaturity": "115",
    "totalProduction": "18211",
    "estimatedSilage": "26.0",
    "milkPerTon": "3285",
    "milkPerAcre": "29979",
    "diseaseScore": "1.8",
    "dmAtHarvest": "48%",
    "nel": "0.69",
    "tdn": "73.4",
    "cp": "8.1",
    "ivtdmd30": "75.5",
    "starch": "25.2",
    "wsc": "5.2",
    "adf": "26.8",
    "aNdf": "47.5",
    "dNdf30": "25.6",
    "nDfd30Percentage": "53.9",
    "year": "2020",
    "season": "Spring",
    "type": "Corn Silage"
  },
  {
    "company": "Syngenta",
    "hybrid": "NK1748-3110",
    "relativeMaturity": "116",
    "totalProduction": "18015",
    "estimatedSilage": "25.7",
    "milkPerTon": "3193",
    "milkPerAcre": "28751",
    "diseaseScore": "1.5",
    "dmAtHarvest": "49%",
    "nel": "0.68",
    "tdn": "71.7",
    "cp": "7.3",
    "ivtdmd30": "73.4",
    "starch": "26.7",
    "wsc": "5.1",
    "adf": "27.0",
    "aNdf": "48.1",
    "dNdf30": "24.2",
    "nDfd30Percentage": "50.3",
    "year": "2020",
    "season": "Spring",
    "type": "Corn Silage"
  },
  {
    "company": "Syngenta",
    "hybrid": "NK1808 3111",
    "relativeMaturity": "117",
    "totalProduction": "21780",
    "estimatedSilage": "31.1",
    "milkPerTon": "3414",
    "milkPerAcre": "36781",
    "diseaseScore": ".",
    "dmAtHarvest": "45%",
    "nel": "0.71",
    "tdn": "74.8",
    "cp": "9.0",
    "ivtdmd30": "76.8",
    "starch": "29.5",
    "wsc": "6.3",
    "adf": "22.4",
    "aNdf": "43.0",
    "dNdf30": "23.0",
    "nDfd30Percentage": "53.5",
    "year": "2020",
    "season": "Spring",
    "type": "Corn Silage"
  },
  {
    "company": "UF",
    "hybrid": "UFR 197",
    "relativeMaturity": "125",
    "totalProduction": "16584",
    "estimatedSilage": "23.7",
    "milkPerTon": "3034",
    "milkPerAcre": "18634",
    "diseaseScore": "0.6",
    "dmAtHarvest": "43%",
    "nel": "0.65",
    "tdn": "70.0",
    "cp": "8.9",
    "ivtdmd30": "71.8",
    "starch": "15.6",
    "wsc": "8.8",
    "adf": "28.9",
    "aNdf": "52.6",
    "dNdf30": "25.8",
    "nDfd30Percentage": "49.1",
    "year": "2020",
    "season": "Spring",
    "type": "Corn Silage"
  },
  {
    "company": "UF",
    "hybrid": "UFR 299",
    "relativeMaturity": "125",
    "totalProduction": "14333",
    "estimatedSilage": "20.5",
    "milkPerTon": "3196",
    "milkPerAcre": "22885",
    "diseaseScore": "0.9",
    "dmAtHarvest": "45%",
    "nel": "0.67",
    "tdn": "72.8",
    "cp": "8.5",
    "ivtdmd30": "73.5",
    "starch": "16.6",
    "wsc": "6.5",
    "adf": "30.2",
    "aNdf": "54.1",
    "dNdf30": "28.0",
    "nDfd30Percentage": "51.8",
    "year": "2020",
    "season": "Spring",
    "type": "Corn Silage"
  },
  {
    "company": "AgraTech",
    "hybrid": "88VT2P",
    "totalProduction": "7360",
    "estimatedSilage": "10.5",
    "milkPerTon": "3056",
    "milkPerAcre": "11266",
    "diseaseScore": "2.0",
    "dmAtHarvest": "26%",
    "nel": "0.66",
    "tdn": "68.6",
    "cp": "8.6",
    "ivtdmd30": "72.6",
    "starch": "20.9",
    "wsc": "5.6",
    "adf": "29.7",
    "aNdf": "51.7",
    "dNdf30": "24.7",
    "nDfd30Percentage": "47.9",
    "year": "2020",
    "season": "Summer",
    "type": "Corn"
  },
  {
    "company": "AgraTech",
    "hybrid": "908VIP",
    "totalProduction": "11298",
    "estimatedSilage": "16.1",
    "milkPerTon": "3334",
    "milkPerAcre": "18842",
    "diseaseScore": "0.9",
    "dmAtHarvest": "30%",
    "nel": "0.70",
    "tdn": "72.4",
    "cp": "8.8",
    "ivtdmd30": "76.6",
    "starch": "27.0",
    "wsc": "4.9",
    "adf": "25.9",
    "aNdf": "46.2",
    "dNdf30": "22.3",
    "nDfd30Percentage": "48.1",
    "year": "2020",
    "season": "Summer",
    "type": "Corn"
  },
  {
    "company": "Augusta seed",
    "hybrid": "A4467-3220GT",
    "relativeMaturity": "117",
    "totalProduction": "10542",
    "estimatedSilage": "15.1",
    "milkPerTon": "3448",
    "milkPerAcre": "18231",
    "diseaseScore": "1.5",
    "dmAtHarvest": "28%",
    "nel": "0.72",
    "tdn": "73.8",
    "cp": "9.0",
    "ivtdmd30": "77.9",
    "starch": "28.6",
    "wsc": "5.4",
    "adf": "24.2",
    "aNdf": "43.2",
    "dNdf30": "20.1",
    "nDfd30Percentage": "46.3",
    "year": "2020",
    "season": "Summer",
    "type": "Corn"
  },
  {
    "company": "Croplan Genetics",
    "hybrid": "S5700",
    "relativeMaturity": "118",
    "totalProduction": "10809",
    "estimatedSilage": "15.4",
    "milkPerTon": "3440",
    "milkPerAcre": "18685",
    "diseaseScore": "0.6",
    "dmAtHarvest": "31%",
    "nel": "0.72",
    "tdn": "73.4",
    "cp": "8.6",
    "ivtdmd30": "78.4",
    "starch": "30.4",
    "wsc": "5.7",
    "adf": "23.5",
    "aNdf": "42.1",
    "dNdf30": "18.9",
    "nDfd30Percentage": "44.8",
    "year": "2020",
    "season": "Summer",
    "type": "Corn"
  },
  {
    "company": "Croplan Genetics",
    "hybrid": "S5900 vt2p",
    "relativeMaturity": "118",
    "totalProduction": "9310",
    "estimatedSilage": "13.3",
    "milkPerTon": "3153",
    "milkPerAcre": "14734",
    "diseaseScore": "1.3",
    "dmAtHarvest": "28%",
    "nel": "0.68",
    "tdn": "69.5",
    "cp": "8.6",
    "ivtdmd30": "72.7",
    "starch": "22.9",
    "wsc": "6.6",
    "adf": "28.2",
    "aNdf": "49.6",
    "dNdf30": "21.7",
    "nDfd30Percentage": "43.5",
    "year": "2020",
    "season": "Summer",
    "type": "Corn"
  },
  {
    "company": "Dekalb",
    "hybrid": "DKC64-44RIB SS",
    "relativeMaturity": "114",
    "totalProduction": "10418",
    "estimatedSilage": "14.9",
    "milkPerTon": "3354",
    "milkPerAcre": "17469",
    "diseaseScore": "1.5",
    "dmAtHarvest": "34%",
    "nel": "0.71",
    "tdn": "72.5",
    "cp": "8.8",
    "ivtdmd30": "78.0",
    "starch": "28.3",
    "wsc": "5.7",
    "adf": "24.2",
    "aNdf": "43.6",
    "dNdf30": "20.8",
    "nDfd30Percentage": "47.8",
    "year": "2020",
    "season": "Summer",
    "type": "Corn"
  },
  {
    "company": "Dekalb",
    "hybrid": "DKC68-69 VT2P",
    "relativeMaturity": "118",
    "totalProduction": "10812",
    "estimatedSilage": "15.4",
    "milkPerTon": "3294",
    "milkPerAcre": "17914",
    "diseaseScore": "0.6",
    "dmAtHarvest": "32%",
    "nel": "0.70",
    "tdn": "71.3",
    "cp": "8.4",
    "ivtdmd30": "75.3",
    "starch": "30.2",
    "wsc": "4.9",
    "adf": "24.4",
    "aNdf": "44.4",
    "dNdf30": "19.0",
    "nDfd30Percentage": "42.6",
    "year": "2020",
    "season": "Summer",
    "type": "Corn"
  },
  {
    "company": "Dekalb",
    "hybrid": "DKC69-16 SS",
    "relativeMaturity": "118",
    "totalProduction": "11226",
    "estimatedSilage": "16.0",
    "milkPerTon": "3420",
    "milkPerAcre": "19287",
    "diseaseScore": "0.5",
    "dmAtHarvest": "29%",
    "nel": "0.72",
    "tdn": "73.0",
    "cp": "9.0",
    "ivtdmd30": "76.5",
    "starch": "29.0",
    "wsc": "4.9",
    "adf": "24.2",
    "aNdf": "43.7",
    "dNdf30": "18.7",
    "nDfd30Percentage": "42.7",
    "year": "2020",
    "season": "Summer",
    "type": "Corn"
  },
  {
    "company": "Dekalb",
    "hybrid": "DKC69-99 TRECEPTA",
    "relativeMaturity": "119",
    "totalProduction": "10709",
    "estimatedSilage": "15.3",
    "milkPerTon": "3374",
    "milkPerAcre": "18035",
    "diseaseScore": "1.3",
    "dmAtHarvest": "33%",
    "nel": "0.71",
    "tdn": "72.4",
    "cp": "8.2",
    "ivtdmd30": "75.4",
    "starch": "31.0",
    "wsc": "4.5",
    "adf": "23.7",
    "aNdf": "43.4",
    "dNdf30": "18.2",
    "nDfd30Percentage": "42.0",
    "year": "2020",
    "season": "Summer",
    "type": "Corn"
  },
  {
    "company": "Dekalb",
    "hybrid": "DKC70-64 SS",
    "relativeMaturity": "119",
    "totalProduction": "12960",
    "estimatedSilage": "18.5",
    "milkPerTon": "3325",
    "milkPerAcre": "21562",
    "diseaseScore": "1.0",
    "dmAtHarvest": "30%",
    "nel": "0.70",
    "tdn": "71.8",
    "cp": "8.8",
    "ivtdmd30": "74.8",
    "starch": "25.7",
    "wsc": "6.7",
    "adf": "25.3",
    "aNdf": "45.2",
    "dNdf30": "19.4",
    "nDfd30Percentage": "42.8",
    "year": "2020",
    "season": "Summer",
    "type": "Corn"
  },
  {
    "company": "Local Seed",
    "hybrid": "LC1688 SSX",
    "relativeMaturity": "116",
    "totalProduction": "10896",
    "estimatedSilage": "15.6",
    "milkPerTon": "3395",
    "milkPerAcre": "18507",
    "diseaseScore": "1.1",
    "dmAtHarvest": "32%",
    "nel": "0.71",
    "tdn": "72.8",
    "cp": "8.8",
    "ivtdmd30": "77.8",
    "starch": "30.6",
    "wsc": "5.7",
    "adf": "23.0",
    "aNdf": "41.7",
    "dNdf30": "18.9",
    "nDfd30Percentage": "45.2",
    "year": "2020",
    "season": "Summer",
    "type": "Corn"
  },
  {
    "company": "Local Seed",
    "hybrid": "LC1898 TC",
    "relativeMaturity": "118",
    "totalProduction": "10272",
    "estimatedSilage": "14.7",
    "milkPerTon": "3450",
    "milkPerAcre": "17792",
    "diseaseScore": "1.3",
    "dmAtHarvest": "34%",
    "nel": "0.72",
    "tdn": "73.6",
    "cp": "8.0",
    "ivtdmd30": "77.9",
    "starch": "33.1",
    "wsc": "4.3",
    "adf": "22.6",
    "aNdf": "40.8",
    "dNdf30": "18.1",
    "nDfd30Percentage": "44.5",
    "year": "2020",
    "season": "Summer",
    "type": "Corn"
  },
  {
    "company": "Local Seed",
    "hybrid": "LC1506 VT2P",
    "relativeMaturity": "115",
    "totalProduction": "11544",
    "estimatedSilage": "16.5",
    "milkPerTon": "3392",
    "milkPerAcre": "19600",
    "diseaseScore": "1.1",
    "dmAtHarvest": "33%",
    "nel": "0.71",
    "tdn": "72.9",
    "cp": "8.4",
    "ivtdmd30": "77.7",
    "starch": "30.2",
    "wsc": "5.3",
    "adf": "24.2",
    "aNdf": "42.9",
    "dNdf30": "19.7",
    "nDfd30Percentage": "45.9",
    "year": "2020",
    "season": "Summer",
    "type": "Corn"
  },
  {
    "company": "Local Seed",
    "hybrid": "LC1707 VT2P",
    "relativeMaturity": "117",
    "totalProduction": "9601",
    "estimatedSilage": "13.7",
    "milkPerTon": "3380",
    "milkPerAcre": "16249",
    "diseaseScore": "1.4",
    "dmAtHarvest": "33%",
    "nel": "0.71",
    "tdn": "72.6",
    "cp": "8.8",
    "ivtdmd30": "76.3",
    "starch": "30.4",
    "wsc": "4.6",
    "adf": "23.6",
    "aNdf": "43.2",
    "dNdf30": "18.6",
    "nDfd30Percentage": "42.7",
    "year": "2020",
    "season": "Summer",
    "type": "Corn"
  },
  {
    "company": "Local Seed",
    "hybrid": "LC1806 VT2P",
    "relativeMaturity": "117",
    "totalProduction": "10154",
    "estimatedSilage": "14.5",
    "milkPerTon": "3400",
    "milkPerAcre": "17292",
    "diseaseScore": "1.4",
    "dmAtHarvest": "31%",
    "nel": "0.72",
    "tdn": "72.8",
    "cp": "8.3",
    "ivtdmd30": "75.5",
    "starch": "33.6",
    "wsc": "3.5",
    "adf": "23.4",
    "aNdf": "41.6",
    "dNdf30": "17.5",
    "nDfd30Percentage": "42.0",
    "year": "2020",
    "season": "Summer",
    "type": "Corn"
  },
  {
    "company": "Pioneer",
    "hybrid": "P30F35 VYHR",
    "relativeMaturity": "135",
    "totalProduction": "10975",
    "estimatedSilage": "15.7",
    "milkPerTon": "3356",
    "milkPerAcre": "18409",
    "diseaseScore": "0.0",
    "dmAtHarvest": "28%",
    "nel": "0.71",
    "tdn": "72.4",
    "cp": "10.1",
    "ivtdmd30": "78.6",
    "starch": "23.3",
    "wsc": "6.4",
    "adf": "25.8",
    "aNdf": "48.2",
    "dNdf30": "23.0",
    "nDfd30Percentage": "47.6",
    "year": "2020",
    "season": "Summer",
    "type": "Corn"
  },
  {
    "company": "Pioneer",
    "hybrid": "P1847 VYHR",
    "relativeMaturity": "118",
    "totalProduction": "10932",
    "estimatedSilage": "15.6",
    "milkPerTon": "3335",
    "milkPerAcre": "18216",
    "diseaseScore": "1.4",
    "dmAtHarvest": "28%",
    "nel": "0.70",
    "tdn": "72.5",
    "cp": "8.8",
    "ivtdmd30": "75.8",
    "starch": "24.3",
    "wsc": "5.3",
    "adf": "27.2",
    "aNdf": "47.4",
    "dNdf30": "22.0",
    "nDfd30Percentage": "46.5",
    "year": "2020",
    "season": "Summer",
    "type": "Corn"
  },
  {
    "company": "Pioneer",
    "hybrid": "P1903 YHR",
    "relativeMaturity": "118",
    "totalProduction": "10206",
    "estimatedSilage": "14.6",
    "milkPerTon": "3417",
    "milkPerAcre": "17504",
    "diseaseScore": "1.0",
    "dmAtHarvest": "29%",
    "nel": "0.71",
    "tdn": "73.5",
    "cp": "9.0",
    "ivtdmd30": "78.1",
    "starch": "27.0",
    "wsc": "5.5",
    "adf": "25.3",
    "aNdf": "44.7",
    "dNdf30": "21.1",
    "nDfd30Percentage": "47.1",
    "year": "2020",
    "season": "Summer",
    "type": "Corn"
  },
  {
    "company": "Syngenta",
    "hybrid": "NK1573-5222",
    "relativeMaturity": "115",
    "totalProduction": "11017",
    "estimatedSilage": "15.7",
    "milkPerTon": "3309",
    "milkPerAcre": "18183",
    "diseaseScore": "1.8",
    "dmAtHarvest": "30%",
    "nel": "0.70",
    "tdn": "71.8",
    "cp": "9.0",
    "ivtdmd30": "76.2",
    "starch": "27.7",
    "wsc": "6.2",
    "adf": "24.9",
    "aNdf": "44.1",
    "dNdf30": "20.3",
    "nDfd30Percentage": "45.9",
    "year": "2020",
    "season": "Summer",
    "type": "Corn"
  },
  {
    "company": "Syngenta",
    "hybrid": "NK1677-3110",
    "relativeMaturity": "116",
    "totalProduction": "12337",
    "estimatedSilage": "17.6",
    "milkPerTon": "3431",
    "milkPerAcre": "21188",
    "diseaseScore": "1.8",
    "dmAtHarvest": "34%",
    "nel": "0.72",
    "tdn": "73.5",
    "cp": "8.5",
    "ivtdmd30": "78.6",
    "starch": "30.8",
    "wsc": "5.5",
    "adf": "23.6",
    "aNdf": "42.9",
    "dNdf30": "19.8",
    "nDfd30Percentage": "46.3",
    "year": "2020",
    "season": "Summer",
    "type": "Corn"
  },
  {
    "company": "Syngenta",
    "hybrid": "NK1748-3110",
    "relativeMaturity": "117",
    "totalProduction": "11607",
    "estimatedSilage": "16.6",
    "milkPerTon": "3394",
    "milkPerAcre": "19773",
    "diseaseScore": "1.4",
    "dmAtHarvest": "32%",
    "nel": "0.71",
    "tdn": "73.2",
    "cp": "9.1",
    "ivtdmd30": "77.2",
    "starch": "27.8",
    "wsc": "4.7",
    "adf": "25.6",
    "aNdf": "45.0",
    "dNdf30": "21.2",
    "nDfd30Percentage": "47.1",
    "year": "2020",
    "season": "Summer",
    "type": "Corn"
  },
  {
    "company": "Alta Seeds",
    "hybrid": "ADV F7232",
    "totalProduction": "10030",
    "estimatedSilage": "14.3",
    "milkPerTon": "2290",
    "milkPerAcre": "11466",
    "diseaseScore": "1.9",
    "lodgingScore": "0",
    "dmAtHarvest": "25%",
    "nel": "0.55",
    "tdn": "59.0",
    "cp": "7.8",
    "ivtdmd30": "45.1",
    "starch": "7.5",
    "wsc": "7.9",
    "adf": "37.3",
    "aNdf": "65.2",
    "dNdf30": "16.0",
    "nDfd30Percentage": "24.6",
    "year": "2020",
    "season": "Summer",
    "type": "Forage Soghum"
  },
  {
    "company": "Alta Seeds",
    "hybrid": "ADV F8322",
    "totalProduction": "9721",
    "estimatedSilage": "13.9",
    "milkPerTon": "2392",
    "milkPerAcre": "11515",
    "diseaseScore": "2.3",
    "lodgingScore": "0",
    "dmAtHarvest": "28%",
    "nel": "0.56",
    "tdn": "60.0",
    "cp": "7.9",
    "ivtdmd30": "46.4",
    "starch": "8.5",
    "wsc": "6.5",
    "adf": "37.8",
    "aNdf": "66.7",
    "dNdf30": "17.0",
    "nDfd30Percentage": "25.3",
    "year": "2020",
    "season": "Summer",
    "type": "Forage Soghum"
  },
  {
    "company": "DynaGro",
    "hybrid": "F72FS05",
    "totalProduction": "10267",
    "estimatedSilage": "14.7",
    "milkPerTon": "2715",
    "milkPerAcre": "13885",
    "diseaseScore": "2.0",
    "lodgingScore": "0",
    "dmAtHarvest": "29%",
    "nel": "0.60",
    "tdn": "65.6",
    "cp": "8.5",
    "ivtdmd30": "45.7",
    "starch": "11.5",
    "wsc": "5.8",
    "adf": "35.4",
    "aNdf": "63.4",
    "dNdf30": "15.2",
    "nDfd30Percentage": "24.1",
    "year": "2020",
    "season": "Summer",
    "type": "Forage Soghum"
  },
  {
    "company": "DynaGro",
    "hybrid": "F74FS23 BMR",
    "totalProduction": "6697",
    "estimatedSilage": "9.6",
    "milkPerTon": "2410",
    "milkPerAcre": "7931",
    "diseaseScore": "1.1",
    "lodgingScore": "1.75",
    "dmAtHarvest": "24%",
    "nel": "0.56",
    "tdn": "61.6",
    "cp": "7.1",
    "ivtdmd30": "46.9",
    "starch": "7.1",
    "wsc": "9.0",
    "adf": "37.8",
    "aNdf": "65.4",
    "dNdf30": "17.8",
    "nDfd30Percentage": "27.4",
    "year": "2020",
    "season": "Summer",
    "type": "Forage Soghum"
  },
  {
    "company": "DynaGro",
    "hybrid": "F74FS72 BMR",
    "totalProduction": "10205",
    "estimatedSilage": "14.6",
    "milkPerTon": "2299",
    "milkPerAcre": "11714",
    "diseaseScore": "2.4",
    "lodgingScore": "0",
    "dmAtHarvest": "25%",
    "nel": "0.55",
    "tdn": "59.2",
    "cp": "7.9",
    "ivtdmd30": "44.7",
    "starch": "7.6",
    "wsc": "7.2",
    "adf": "38.1",
    "aNdf": "65.9",
    "dNdf30": "16.4",
    "nDfd30Percentage": "25.0",
    "year": "2020",
    "season": "Summer",
    "type": "Forage Soghum"
  },
  {
    "company": "DynaGro",
    "hybrid": "F75FS13",
    "totalProduction": "9324",
    "estimatedSilage": "13.3",
    "milkPerTon": "2213",
    "milkPerAcre": "10381",
    "diseaseScore": "1.4",
    "lodgingScore": "0",
    "dmAtHarvest": "22%",
    "nel": "0.54",
    "tdn": "57.4",
    "cp": "8.0",
    "ivtdmd30": "43.1",
    "starch": "7.4",
    "wsc": "7.8",
    "adf": "37.4",
    "aNdf": "64.4",
    "dNdf30": "14.8",
    "nDfd30Percentage": "22.9",
    "year": "2020",
    "season": "Summer",
    "type": "Forage Soghum"
  },
  {
    "company": "DynaGro",
    "hybrid": "Super Sile 20",
    "totalProduction": "7949",
    "estimatedSilage": "11.4",
    "milkPerTon": "2484",
    "milkPerAcre": "9174",
    "diseaseScore": "2.4",
    "lodgingScore": "0",
    "dmAtHarvest": "25%",
    "nel": "0.57",
    "tdn": "61.9",
    "cp": "9.7",
    "ivtdmd30": "46.4",
    "starch": "7.2",
    "wsc": "6.0",
    "adf": "38.0",
    "aNdf": "66.4",
    "dNdf30": "18.3",
    "nDfd30Percentage": "27.6",
    "year": "2020",
    "season": "Summer",
    "type": "Forage Soghum"
  },
  {
    "company": "DynaGro",
    "hybrid": "Super Sile 30",
    "totalProduction": "11257",
    "estimatedSilage": "16.1",
    "milkPerTon": "2919",
    "milkPerAcre": "16720",
    "diseaseScore": "2.8",
    "lodgingScore": "0",
    "dmAtHarvest": "26%",
    "nel": "0.63",
    "tdn": "69.3",
    "cp": "9.6",
    "ivtdmd30": "47.6",
    "starch": "10.2",
    "wsc": "6.1",
    "adf": "34.9",
    "aNdf": "63.9",
    "dNdf30": "17.4",
    "nDfd30Percentage": "27.4",
    "year": "2020",
    "season": "Summer",
    "type": "Forage Soghum"
  },
  {
    "company": "MOJO Seed Enterprises",
    "hybrid": "OPAL",
    "totalProduction": "10781",
    "estimatedSilage": "15.4",
    "milkPerTon": "2240",
    "milkPerAcre": "12125",
    "diseaseScore": "1.9",
    "lodgingScore": "0",
    "dmAtHarvest": "26%",
    "nel": "0.54",
    "tdn": "58.5",
    "cp": "7.5",
    "ivtdmd30": "47.8",
    "starch": "8.1",
    "wsc": "8.5",
    "adf": "35.8",
    "aNdf": "64.7",
    "dNdf30": "16.8",
    "nDfd30Percentage": "26.4",
    "year": "2020",
    "season": "Summer",
    "type": "Forage Soghum"
  },
  {
    "company": "Sorghum Partners",
    "hybrid": "NK300",
    "totalProduction": "9795",
    "estimatedSilage": "14.0",
    "milkPerTon": "2450",
    "milkPerAcre": "11927",
    "diseaseScore": "2.3",
    "lodgingScore": "0",
    "dmAtHarvest": "23%",
    "nel": "0.57",
    "tdn": "62.2",
    "cp": "7.8",
    "ivtdmd30": "50.0",
    "starch": "5.2",
    "wsc": "8.9",
    "adf": "37.4",
    "aNdf": "66.8",
    "dNdf30": "19.7",
    "nDfd30Percentage": "29.5",
    "year": "2020",
    "season": "Summer",
    "type": "Forage Soghum"
  },
  {
    "company": "Sorghum Partners",
    "hybrid": "SP3904 BD BMR",
    "totalProduction": "9182",
    "estimatedSilage": "13.1",
    "milkPerTon": "2360",
    "milkPerAcre": "10753",
    "diseaseScore": "1.8",
    "lodgingScore": "0",
    "dmAtHarvest": "26%",
    "nel": "0.56",
    "tdn": "59.8",
    "cp": "9.0",
    "ivtdmd30": "45.7",
    "starch": "7.5",
    "wsc": "5.2",
    "adf": "39.0",
    "aNdf": "68.1",
    "dNdf30": "18.4",
    "nDfd30Percentage": "27.0",
    "year": "2020",
    "season": "Summer",
    "type": "Forage Soghum"
  },
  {
    "company": "Sorghum Partners",
    "hybrid": "SP3905 BD BMR",
    "totalProduction": "7824",
    "estimatedSilage": "11.2",
    "milkPerTon": "3238",
    "milkPerAcre": "12700",
    "diseaseScore": "1.4",
    "lodgingScore": "0",
    "dmAtHarvest": "26%",
    "nel": "0.68",
    "tdn": "74.0",
    "cp": "8.9",
    "ivtdmd30": "45.8",
    "starch": "13.5",
    "wsc": "6.5",
    "adf": "33.0",
    "aNdf": "58.5",
    "dNdf30": "13.0",
    "nDfd30Percentage": "22.2",
    "year": "2020",
    "season": "Summer",
    "type": "Forage Soghum"
  },
  {
    "company": "Sorghum Partners",
    "hybrid": "SS405",
    "totalProduction": "9035",
    "estimatedSilage": "12.9",
    "milkPerTon": "2800",
    "milkPerAcre": "12746",
    "diseaseScore": "2.8",
    "lodgingScore": "0",
    "dmAtHarvest": "26%",
    "nel": "0.61",
    "tdn": "68.3",
    "cp": "7.9",
    "ivtdmd30": "49.3",
    "starch": "9.3",
    "wsc": "9.3",
    "adf": "34.0",
    "aNdf": "61.5",
    "dNdf30": "16.8",
    "nDfd30Percentage": "27.4",
    "year": "2020",
    "season": "Summer",
    "type": "Forage Soghum"
  },
  {
    "company": "Alta Seeds",
    "hybrid": "ADV S6504",
    "totalProduction": "6772",
    "estimatedSilage": "9.7",
    "milkPerTon": "1519",
    "milkPerAcre": "5112",
    "diseaseScore": "1.0",
    "lodgingScore": "2.25",
    "dmAtHarvest": "20%",
    "nel": "0.44",
    "tdn": "45.9",
    "cp": "11.2",
    "ivtdmd30": "42.2",
    "starch": "0.8",
    "wsc": "4.1",
    "adf": "43.4",
    "aNdf": "73.2",
    "dNdf30": "23.0",
    "nDfd30Percentage": "31.4",
    "year": "2020",
    "season": "Summer",
    "type": "Soghum Sudan"
  },
  {
    "company": "Alta Seeds",
    "hybrid": "ADV XS167",
    "totalProduction": "7848",
    "estimatedSilage": "11.2",
    "milkPerTon": "1731",
    "milkPerAcre": "7224",
    "diseaseScore": "1.4",
    "lodgingScore": "0.5",
    "dmAtHarvest": "30%",
    "nel": "0.47",
    "tdn": "48.5",
    "cp": "8.0",
    "ivtdmd30": "43.1",
    "starch": "2.2",
    "wsc": "6.9",
    "adf": "40.7",
    "aNdf": "72.1",
    "dNdf30": "20.9",
    "nDfd30Percentage": "29.0",
    "year": "2020",
    "season": "Summer",
    "type": "Soghum Sudan"
  },
  {
    "company": "DynaGro",
    "hybrid": "Fullgraze II",
    "totalProduction": "10196",
    "estimatedSilage": "14.6",
    "milkPerTon": "1493",
    "milkPerAcre": "7357",
    "diseaseScore": "1.4",
    "lodgingScore": "1.5",
    "dmAtHarvest": "34%",
    "nel": "0.44",
    "tdn": "43.9",
    "cp": "6.9",
    "ivtdmd30": "41.2",
    "starch": "2.6",
    "wsc": "7.0",
    "adf": "41.9",
    "aNdf": "73.9",
    "dNdf30": "19.4",
    "nDfd30Percentage": "26.3",
    "year": "2020",
    "season": "Summer",
    "type": "Soghum Sudan"
  },
  {
    "company": "DynaGro",
    "hybrid": "Fullgraze II BMR",
    "totalProduction": "12397",
    "estimatedSilage": "17.7",
    "milkPerTon": "1866",
    "milkPerAcre": "11995",
    "diseaseScore": "1.0",
    "lodgingScore": "2.375",
    "dmAtHarvest": "27%",
    "nel": "0.49",
    "tdn": "50.9",
    "cp": "8.3",
    "ivtdmd30": "44.7",
    "starch": "1.4",
    "wsc": "7.6",
    "adf": "40.0",
    "aNdf": "71.2",
    "dNdf30": "21.5",
    "nDfd30Percentage": "30.2",
    "year": "2020",
    "season": "Summer",
    "type": "Soghum Sudan"
  },
  {
    "company": "DynaGro",
    "hybrid": "TopTon",
    "totalProduction": "10740",
    "estimatedSilage": "15.3",
    "milkPerTon": "1735",
    "milkPerAcre": "8778",
    "diseaseScore": "1.4",
    "lodgingScore": "1.25",
    "dmAtHarvest": "30%",
    "nel": "0.48",
    "tdn": "47.7",
    "cp": "7.5",
    "ivtdmd30": "44.4",
    "starch": "6.2",
    "wsc": "7.3",
    "adf": "39.4",
    "aNdf": "68.1",
    "dNdf30": "18.1",
    "nDfd30Percentage": "26.5",
    "year": "2020",
    "season": "Summer",
    "type": "Soghum Sudan"
  }
]